vicregaddon/__init__.py
vicregaddon/vicregaddon.py
vicregaddon-0.0.4.dist-info/LICENSE
vicregaddon-0.0.4.dist-info/METADATA
vicregaddon-0.0.4.dist-info/WHEEL
vicregaddon-0.0.4.dist-info/top_level.txt
vicregaddon-0.0.4.dist-info/RECORD
