Metadata-Version: 2.1
Name: vicregaddon
Version: 0.0.4
Summary: A lightweight and modular parallel PyTorch implementation of VICReg (intended for audio, but will try to be general)
Home-page: https://github.com/drscotthawley/vicregaddon
Author: Scott H. Hawley
Author-email: scott.hawley@belmont.edu
License: MIT
License-File: LICENSE
Requires-Dist: torch
Requires-Dist: einops
